[
    {
        "id": 1,
        "nome": "Ana",
        "idade": 28,
        "email": "ana@example.com"
    },
    {
        "id": 2,
        "nome": "Bruno",
        "idade": 34,
        "email": "bruno@example.com"
    },
    {
        "id": 3,
        "nome": "Carlos",
        "idade": 45,
        "email": "carlos@example.com"
    },
    {
        "id": 4,
        "nome": "Diana",
        "idade": 32,
        "email": "diana@example.com"
    },
    {
        "id": 5,
        "nome": "Eduardo",
        "idade": 29,
        "email": "eduardo@example.com"
    },
    {
        "id": 6,
        "nome": "Fernanda",
        "idade": 31,
        "email": "fernanda@example.com"
    },
    {
        "id": 7,
        "nome": "Gustavo",
        "idade": 40,
        "email": "gustavo@example.com"
    },
    {
        "id": 8,
        "nome": "Heloísa",
        "idade": 27,
        "email": "heloisa@example.com"
    },
    {
        "id": 9,
        "nome": "Igor",
        "idade": 35,
        "email": "igor@example.com"
    },
    {
        "id": 10,
        "nome": "Juliana",
        "idade": 30,
        "email": "juliana@example.com"
    }
]
